check11/__init__.py
check11/base_test.py
check11/prompt_helpers.py
check11-2026.11.11.dist-info/licenses/LICENSE
check11-2026.11.11.dist-info/METADATA
check11-2026.11.11.dist-info/WHEEL
check11-2026.11.11.dist-info/entry_points.txt
check11-2026.11.11.dist-info/top_level.txt
check11-2026.11.11.dist-info/RECORD
