Metadata-Version: 2.4
Name: check11
Version: 2026.11.11
Summary: Check11 by Monze.EU makes you dig coding
Author-email: "Victor G.B. Peters" <victor@jeex.eu>
Classifier: Programming Language :: Python :: 3
Classifier: License :: OSI Approved :: MIT License
Classifier: Operating System :: OS Independent
Requires-Python: >=3.11
License-File: LICENSE
Requires-Dist: PyYAML
Requires-Dist: pytz
Requires-Dist: certifi
Requires-Dist: requests
Requires-Dist: pyperclip
Requires-Dist: colorama
Requires-Dist: platformdirs
Dynamic: license-file
